django_smart_validate-0.1.0.dist-info/licenses/LICENSE
smart_validate/ mixins.py
smart_validate/__init__.py
smart_validate/validators.py
django_smart_validate-0.1.0.dist-info/METADATA
django_smart_validate-0.1.0.dist-info/WHEEL
django_smart_validate-0.1.0.dist-info/top_level.txt
django_smart_validate-0.1.0.dist-info/RECORD
