Metadata-Version: 2.4
Name: django-smart-validate
Version: 0.1.0
Summary: Smart reusable validators for Django models & forms.
Author: ProgrammerHasan
Classifier: Framework :: Django
Classifier: Programming Language :: Python :: 3
Requires-Python: >=3.7
License-File: LICENSE
Requires-Dist: Django>=3.2
Dynamic: author
Dynamic: classifier
Dynamic: description
Dynamic: description-content-type
Dynamic: license-file
Dynamic: requires-dist
Dynamic: requires-python
Dynamic: summary
